[
    {
      "id": "R7LpKMq3",
      "img": "",
      "title": "Understanding CSS Loaders",
      "name": "Ravi Sharma",
      "username": "ravisharma",
      "likes": 58,
      "liked_by": [
        { "username": "priyanair", "DP": "" },
        { "username": "amitsingh", "DP": "" },
        { "username": "nehagupta", "DP": "" }
      ],
      "comment": 10,
      "views": 245,
      "Created_on": "November 12, 2023",
      "Updated_on": "January 15, 2024"
    },
    { 
      "id": "N8LqPMv2",
      "img": "",
      "title": "Advanced CSS Animations",
      "name": "Neha Gupta",
      "username": "nehagupta",
      "likes": 73,
      "liked_by": [
        { "username": "ravisharma", "DP": "" },
        { "username": "karanjohar", "DP": "" },
        { "username": "anjalidas", "DP": "" }
      ],
      "comment": 15,
      "views": 378,
      "Created_on": "March 1, 2024",
      "Updated_on": "April 12, 2024"
    },
    {
      "id": "P9MqRTv6",
      "img": "",
      "title": "Responsive Design with Flexbox",
      "name": "Karan Johar",
      "username": "karanjohar",
      "likes": 64,
      "liked_by": [
        { "username": "priyanair", "DP": "" },
        { "username": "anjalidas", "DP": "" },
        { "username": "amitsingh", "DP": "" }
      ],
      "comment": 12,
      "views": 301,
      "Created_on": "December 15, 2023",
      "Updated_on": "February 10, 2024"
    },
    {
      "id": "Q5LPKN8x",
      "img": "",
      "title": "Mastering CSS Grid",
      "name": "Anjali Das",
      "username": "anjalidas",
      "likes": 89,
      "liked_by": [
        { "username": "nehagupta", "DP": "" },
        { "username": "amitsingh", "DP": "" },
        { "username": "priyanair", "DP": "" }
      ],
      "comment": 18,
      "views": 460,
      "Created_on": "February 18, 2024",
      "Updated_on": "June 20, 2024"
    },
    {
      "id": "L2MPTvQ9",
      "img": "",
      "title": "Building Scalable UI with CSS",
      "name": "Priya Nair",
      "username": "priyanair",
      "likes": 92,
      "liked_by": [
        { "username": "nehagupta", "DP": "" },
        { "username": "ravisharma", "DP": "" },
        { "username": "anjalidas", "DP": "" }
      ],
      "comment": 14,
      "views": 482,
      "Created_on": "April 15, 2024",
      "Updated_on": "June 5, 2024"
    },
    {
      "id": "R8NLqMT3",
      "img": "",
      "title": "CSS Transitions Made Easy",
      "name": "Amit Singh",
      "username": "amitsingh",
      "likes": 71,
      "liked_by": [
        { "username": "karanjohar", "DP": "" },
        { "username": "anjalidas", "DP": "" },
        { "username": "nehagupta", "DP": "" }
      ],
      "comment": 11,
      "views": 390,
      "Created_on": "January 20, 2024",
      "Updated_on": "May 10, 2024"
    },
    {
      "id": "Q7LPMKT8",
      "img": "",
      "title": "CSS Tips for Beginners",
      "name": "Rajesh Kumar",
      "username": "rajeshkumar",
      "likes": 45,
      "liked_by": [
        { "username": "amitsingh", "DP": "" },
        { "username": "nehagupta", "DP": "" },
        { "username": "ravisharma", "DP": "" }
      ],
      "comment": 13,
      "views": 290,
      "Created_on": "October 5, 2023",
      "Updated_on": "March 30, 2024"
    },
    {
      "id": "M3TvPQ5L",
      "img": "",
      "title": "CSS Hacks for Developers",
      "name": "Meera Iyer",
      "username": "meeraiyer",
      "likes": 54,
      "liked_by": [
        { "username": "rajeshkumar", "DP": "" },
        { "username": "amitsingh", "DP": "" },
        { "username": "karanjohar", "DP": "" }
      ],
      "comment": 17,
      "views": 325,
      "Created_on": "November 1, 2023",
      "Updated_on": "April 22, 2024"
    },
    {
      "id": "K2LMNRT9",
      "img": "",
      "title": "Designing with Media Queries",
      "name": "Sanjay Mehta",
      "username": "sanjaymehta",
      "likes": 65,
      "liked_by": [
        { "username": "meeraiyer", "DP": "" },
        { "username": "priyanair", "DP": "" },
        { "username": "anjalidas", "DP": "" }
      ],
      "comment": 20,
      "views": 410,
      "Created_on": "January 12, 2024",
      "Updated_on": "May 25, 2024"
    },
    {
      "id": "N9LPQT5M",
      "img": "",
      "title": "Customizing Buttons with CSS",
      "name": "Arjun Rao",
      "username": "arjunrao",
      "likes": 78,
      "liked_by": [
        { "username": "sanjaymehta", "DP": "" },
        { "username": "ravisharma", "DP": "" },
        { "username": "meeraiyer", "DP": "" }
      ],
      "comment": 22,
      "views": 400,
      "Created_on": "December 2, 2023",
      "Updated_on": "June 11, 2024"
    },
    {
      "id": "V3TKJ7Q6",
      "img": "",
      "title": "Building User-Friendly Navigation",
      "name": "Tanuja Reddy",
      "username": "tanujareddy",
      "likes": 68,
      "liked_by": [
        { "username": "karanjohar", "DP": "" },
        { "username": "priyanair", "DP": "" },
        { "username": "anjalidas", "DP": "" }
      ],
      "comment": 16,
      "views": 335,
      "Created_on": "September 25, 2023",
      "Updated_on": "May 5, 2024"
    },
    {
      "id": "X8TNVQ3Z",
      "img": "",
      "title": "Optimizing CSS for Performance",
      "name": "Sushma Patel",
      "username": "sushmapatel",
      "likes": 55,
      "liked_by": [
        { "username": "tanujareddy", "DP": "" },
        { "username": "amitsingh", "DP": "" },
        { "username": "nehagupta", "DP": "" }
      ],
      "comment": 19,
      "views": 280,
      "Created_on": "October 10, 2023",
      "Updated_on": "March 8, 2024"
    },
    {
      "id": "Z7LKJ4M8",
      "img": "",
      "title": "CSS for Mobile Optimization",
      "name": "Sandeep Yadav",
      "username": "sandeepyadav",
      "likes": 80,
      "liked_by": [
        { "username": "ravisharma", "DP": "" },
        { "username": "priyanair", "DP": "" },
        { "username": "karanjohar", "DP": "" }
      ],
      "comment": 14,
      "views": 450,
      "Created_on": "February 20, 2024",
      "Updated_on": "April 30, 2024"
    },
    {
      "id": "B9KJG2W5",
      "img": "",
      "title": "Flexbox Layout for Beginners",
      "name": "Rohit Singh",
      "username": "rohitsingh",
      "likes": 58,
      "liked_by": [
        { "username": "sushmapatel", "DP": "" },
        { "username": "karanjohar", "DP": "" },
        { "username": "nehagupta", "DP": "" }
      ],
      "comment": 13,
      "views": 312,
      "Created_on": "January 8, 2024",
      "Updated_on": "February 28, 2024"
    },
    {
      "id": "C2T9VJ7X",
      "img": "",
      "title": "CSS Flexbox vs Grid",
      "name": "Manoj Tripathi",
      "username": "manojtripathi",
      "likes": 77,
      "liked_by": [
        { "username": "rohitsingh", "DP": "" },
        { "username": "priyanair", "DP": "" },
        { "username": "sushmapatel", "DP": "" }
      ],
      "comment": 11,
      "views": 400,
      "Created_on": "December 3, 2023",
      "Updated_on": "March 25, 2024"
    },
    {
      "id": "A7L9M8Q2",
      "img": "",
      "title": "Using CSS Variables in Projects",
      "name": "Kavita Rai",
      "username": "kavitrai",
      "likes": 63,
      "liked_by": [
        { "username": "karanjohar", "DP": "" },
        { "username": "manojtripathi", "DP": "" },
        { "username": "nehagupta", "DP": "" }
      ],
      "comment": 18,
      "views": 355,
      "Created_on": "January 10, 2024",
      "Updated_on": "April 20, 2024"
    },
    {
      "id": "Q6V7LR4W",
      "img": "",
      "title": "Mastering CSS Media Queries",
      "name": "Harshit Patel",
      "username": "harshitpatel",
      "likes": 90,
      "liked_by": [
        { "username": "kavitrai", "DP": "" },
        { "username": "rohitsingh", "DP": "" },
        { "username": "sushmapatel", "DP": "" }
      ],
      "comment": 21,
      "views": 475,
      "Created_on": "February 14, 2024",
      "Updated_on": "May 1, 2024"
    },
    {
      "id": "J8TKW6X2",
      "img": "",
      "title": "Efficient CSS Debugging Techniques",
      "name": "Deepak Kumar",
      "username": "deepakkumar",
      "likes": 85,
      "liked_by": [
        { "username": "harshitpatel", "DP": "" },
        { "username": "tanujareddy", "DP": "" },
        { "username": "manojtripathi", "DP": "" }
      ],
      "comment": 9,
      "views": 270,
      "Created_on": "November 5, 2023",
      "Updated_on": "March 2, 2024"
    },
    {
      "id": "S4KLQJ3X",
      "img": "",
      "title": "CSS Best Practices",
      "name": "Priya Yadav",
      "username": "priyayadav",
      "likes": 79,
      "liked_by": [
        { "username": "deepakkumar", "DP": "" },
        { "username": "manojtripathi", "DP": "" },
        { "username": "sandeepyadav", "DP": "" }
      ],
      "comment": 12,
      "views": 330,
      "Created_on": "December 12, 2023",
      "Updated_on": "June 10, 2024"
    },
    {
      "id": "K8LPQJ6M",
      "img": "",
      "title": "Building Accessible Web with CSS",
      "name": "Vijay Reddy",
      "username": "vijayreddy",
      "likes": 64,
      "liked_by": [
        { "username": "sandeepyadav", "DP": "" },
        { "username": "tanujareddy", "DP": "" },
        { "username": "karanjohar", "DP": "" }
      ],
      "comment": 16,
      "views": 390,
      "Created_on": "January 30, 2024",
      "Updated_on": "April 15, 2024"
    },
    {
      "id": "P4V5M2R7",
      "img": "",
      "title": "Understanding Box Model in CSS",
      "name": "Nikhil Kumar",
      "username": "nikhilkumar",
      "likes": 67,
      "liked_by": [
        { "username": "vijayreddy", "DP": "" },
        { "username": "karanjohar", "DP": "" },
        { "username": "sushmapatel", "DP": "" }
      ],
      "comment": 13,
      "views": 278,
      "Created_on": "October 18, 2023",
      "Updated_on": "February 5, 2024"
    }
  ]
  